opendata_pipeline/__init__.py
opendata_pipeline/__main__.py
opendata_pipeline/analyze.py
opendata_pipeline/extract_drugs.py
opendata_pipeline/fetch.py
opendata_pipeline/geocode.py
opendata_pipeline/main.py
opendata_pipeline/manage_config.py
opendata_pipeline/models.py
opendata_pipeline/spatial_join.py
opendata_pipeline/utils.py
opendata_pipeline-0.3.3.dist-info/METADATA
opendata_pipeline-0.3.3.dist-info/WHEEL
opendata_pipeline-0.3.3.dist-info/entry_points.txt
opendata_pipeline-0.3.3.dist-info/licenses/LICENSE
opendata_pipeline-0.3.3.dist-info/RECORD
