Metadata-Version: 2.3
Name: opendata-pipeline
Version: 0.3.3
Summary: A pipeline for processing open medical examier's data using GitHub Actions CI/CD.
Author-email: Nick Anthony <nanthony007@gmail.com>
License: MIT
Requires-Python: >=3.13
Requires-Dist: geopandas>=1.0.1
Requires-Dist: httpx>=0.27.2
Requires-Dist: orjson>=3.10.11
Requires-Dist: pydantic-settings>=2.6.1
Requires-Dist: pydantic>=2.9.2
Requires-Dist: rich>=13.9.4
Requires-Dist: rtree>=1.3.0
Requires-Dist: typer>=0.13.0
